circuit_synth/__init__.py
circuit_synth/ai_integration/__init__.py
circuit_synth/ai_integration/logging_system.py
circuit_synth/ai_integration/stm32_search_helper.py
circuit_synth/ai_integration/agents/debugging_agent.py
circuit_synth/ai_integration/claude/__init__.py
circuit_synth/ai_integration/claude/circuit_design_rules.py
circuit_synth/ai_integration/claude/commands.py
circuit_synth/ai_integration/claude/enhanced_circuit_agent.py
circuit_synth/ai_integration/claude/agents/__init__.py
circuit_synth/ai_integration/claude/agents/circuit_creator_agent.py
circuit_synth/ai_integration/claude/agents/circuit_design_agents.py
circuit_synth/ai_integration/claude/agents/circuit_project_creator.py
circuit_synth/ai_integration/claude/agents/circuit_syntax_fixer.py
circuit_synth/ai_integration/claude/agents/circuit_validation_agent.py
circuit_synth/ai_integration/claude/agents/contributor_agent.py
circuit_synth/ai_integration/claude/agents/test_plan_agent.py
circuit_synth/ai_integration/component_info/__init__.py
circuit_synth/ai_integration/component_info/microcontrollers/__init__.py
circuit_synth/ai_integration/component_info/microcontrollers/modm_device_search.py
circuit_synth/ai_integration/plugins/__init__.py
circuit_synth/ai_integration/plugins/ai_design_bridge.py
circuit_synth/ai_integration/validation/__init__.py
circuit_synth/ai_integration/validation/real_time_check.py
circuit_synth/ai_integration/validation/simple_validator.py
circuit_synth/component_placement/__init__.py
circuit_synth/component_placement/force_directed_layout.py
circuit_synth/component_placement/geometry.py
circuit_synth/component_placement/placement.py
circuit_synth/component_placement/wire_routing.py
circuit_synth/core/__init__.py
circuit_synth/core/_interfaces.py
circuit_synth/core/_logger.py
circuit_synth/core/annotations.py
circuit_synth/core/circuit.py
circuit_synth/core/component.py
circuit_synth/core/component_replacement.py
circuit_synth/core/decorators.py
circuit_synth-0.12.1.dist-info/licenses/LICENSE
circuit_synth-0.12.1.dist-info/METADATA
circuit_synth-0.12.1.dist-info/WHEEL
circuit_synth-0.12.1.dist-info/entry_points.txt
circuit_synth-0.12.1.dist-info/top_level.txt
circuit_synth-0.12.1.dist-info/RECORD
