Metadata-Version: 2.4
Name: circuit_synth
Version: 0.12.1
Summary: Pythonic circuit design for production-ready KiCad projects
Author-email: Circuit Synth Contributors <contact@circuitsynth.com>
License-Expression: MIT
Project-URL: Homepage, https://github.com/circuit-synth/circuit-synth
Project-URL: Documentation, https://circuit-synth.readthedocs.io
Project-URL: Repository, https://github.com/circuit-synth/circuit-synth
Project-URL: Issues, https://github.com/circuit-synth/circuit-synth/issues
Keywords: circuit,design,kicad,electronics,pcb,schematic
Classifier: Development Status :: 4 - Beta
Classifier: Intended Audience :: Developers
Classifier: Programming Language :: Python :: 3
Classifier: Programming Language :: Python :: 3.12
Classifier: Topic :: Software Development :: Libraries :: Python Modules
Classifier: Topic :: Scientific/Engineering :: Electronic Design Automation (EDA)
Classifier: Operating System :: OS Independent
Requires-Python: >=3.12
License-File: LICENSE
Requires-Dist: numpy>=1.20.0
Requires-Dist: scipy>=1.7.0
Requires-Dist: matplotlib>=3.3.0
Requires-Dist: networkx>=2.6.0
Requires-Dist: pydantic>=2.0.0
Requires-Dist: PyYAML>=5.4.0
Requires-Dist: click>=8.0.0
Requires-Dist: rich>=10.0.0
Requires-Dist: loguru>=0.5.0
Requires-Dist: psutil>=5.9.0
Requires-Dist: cachetools>=5.3.0
Requires-Dist: kicad-sch-api>=0.5.5
Requires-Dist: packaging>=21.0
Requires-Dist: sexpdata>=0.0.3
Requires-Dist: aiohttp>=3.9.0
Requires-Dist: aiofiles>=23.2.0
Requires-Dist: fastapi>=0.100.0
Requires-Dist: uvicorn>=0.20.0
Requires-Dist: requests>=2.28.0
Requires-Dist: beautifulsoup4>=4.11.0
Requires-Dist: lxml>=6.0.0
Requires-Dist: pyspice>=1.5
Requires-Dist: twine>=6.1.0
Requires-Dist: openai>=1.0.0
Requires-Dist: python-dotenv>=1.0.0
Provides-Extra: dev
Requires-Dist: pytest>=7.0.0; extra == "dev"
Requires-Dist: pytest-cov>=3.0.0; extra == "dev"
Requires-Dist: pytest-mock>=3.14.0; extra == "dev"
Requires-Dist: pytest-env>=1.1.0; extra == "dev"
Requires-Dist: black>=22.0.0; extra == "dev"
Requires-Dist: isort>=5.10.0; extra == "dev"
Requires-Dist: flake8>=4.0.0; extra == "dev"
Requires-Dist: mypy>=0.950; extra == "dev"
Requires-Dist: types-PyYAML>=6.0.0; extra == "dev"
Requires-Dist: pre-commit>=2.17.0; extra == "dev"
Provides-Extra: claude
Requires-Dist: claude-code-sdk>=0.0.17; extra == "claude"
Provides-Extra: fast-generation
Requires-Dist: google-adk>=0.1.0; extra == "fast-generation"
Requires-Dist: asyncio-mqtt>=0.16.0; extra == "fast-generation"
Provides-Extra: test
Requires-Dist: pytest>=7.0.0; extra == "test"
Requires-Dist: pytest-mock>=3.14.0; extra == "test"
Requires-Dist: pytest-asyncio>=0.24.0; extra == "test"
Requires-Dist: memory-profiler>=0.60.0; extra == "test"
Requires-Dist: hypothesis>=6.0.0; extra == "test"
Dynamic: license-file
